{
  "kind": "singleType",
  "collectionName": "homepages",
  "info": {
    "singularName": "homepage",
    "pluralName": "homepages",
    "displayName": "Homepage",
    "description": "Content structure for the main homepage."
  },
  "options": {
    "draftAndPublish": true
  },
  "pluginOptions": {},
  "attributes": {
    "heroTitle": {
      "type": "string",
      "required": true
    },
    "heroBackgroundImage": {
      "type": "media",
      "multiple": false,
      "required": true,
      "allowedTypes": [
        "images"
      ]
    },
    "cardSectionTitle": {
      "type": "string"
    },
    "cards": {
      "type": "component",
      "repeatable": true,
      "component": "layout.homepage-card",
      "required": true
    }
  }
}